{
  "metadata": {
    "timestamp": "2026-01-24T22:20:31.772717",
    "periodo_entrenamiento": {
      "fecha_inicio": "2025-09-29",
      "fecha_fin": "2025-10-03",
      "descripcion": "Período de alta actividad: 29 sep - 3 oct 2025 (Lun-Vie)"
    },
    "configuracion_modelo": {
      "n_estimators": 100,
      "max_depth": 6,
      "learning_rate": 0.1,
      "subsample": 0.8,
      "colsample_bytree": 0.8,
      "random_state": 42
    }
  },
  "metricas": {
    "entrenamiento": {
      "modelo_cantidad": {
        "rmse": 1.8225343237422416,
        "mae": 1.3832980604238914,
        "r2_score": 0.1738531827559251
      },
      "modelo_prioridad": {
        "rmse": 0.3406763975964153,
        "mae": 0.18100803586798656,
        "r2_score": 0.9266657663425164
      },
      "samples_train": 567,
      "samples_test": 142,
      "features_count": 33
    },
    "comparacion": {
      "base": {
        "global": {
          "mae": 122.10416666666667,
          "rmse": 140.08501882785325,
          "r2_score": -2.349761910688948,
          "mape": 83.14029267833617,
          "total_predicho": 1087.0,
          "total_real": 6948.0
        },
        "por_producto": {
          "Pollo (tacos)": {
            "mae": 148.33333333333334,
            "rmse": 149.53037595529992,
            "mape": 83.08333333333333,
            "errores_por_dia": {
              "Lunes": -124.0,
              "Martes": -142.0,
              "Miércoles": -126.0,
              "Jueves": -166.0,
              "Viernes": -172.0,
              "Sábado": -160.0
            },
            "predicciones": {
              "Lunes": 76.0,
              "Martes": 18.0,
              "Miércoles": 34.0,
              "Jueves": 34.0,
              "Viernes": 28.0,
              "Sábado": 0.0
            },
            "reales": {
              "Lunes": 200,
              "Martes": 160,
              "Miércoles": 160,
              "Jueves": 200,
              "Viernes": 200,
              "Sábado": 160
            }
          },
          "Bistec (tacos)": {
            "mae": 200.33333333333334,
            "rmse": 201.03565189620804,
            "mape": 77.30555555555556,
            "errores_por_dia": {
              "Lunes": -206.0,
              "Martes": -178.0,
              "Miércoles": -180.0,
              "Jueves": -214.0,
              "Viernes": -224.0,
              "Sábado": -200.0
            },
            "predicciones": {
              "Lunes": 94.0,
              "Martes": 62.0,
              "Miércoles": 59.99999999999999,
              "Jueves": 86.0,
              "Viernes": 76.0,
              "Sábado": 0.0
            },
            "reales": {
              "Lunes": 300,
              "Martes": 240,
              "Miércoles": 240,
              "Jueves": 300,
              "Viernes": 300,
              "Sábado": 200
            }
          },
          "Longaniza (tacos)": {
            "mae": 213.33333333333334,
            "rmse": 216.299175526245,
            "mape": 98.52777777777779,
            "errores_por_dia": {
              "Lunes": -193.0,
              "Martes": -197.0,
              "Miércoles": -198.0,
              "Jueves": -199.0,
              "Viernes": -293.0,
              "Sábado": -200.0
            },
            "predicciones": {
              "Lunes": 7.0,
              "Martes": 3.0,
              "Miércoles": 2.0,
              "Jueves": 1.0,
              "Viernes": 7.0,
              "Sábado": 0.0
            },
            "reales": {
              "Lunes": 200,
              "Martes": 200,
              "Miércoles": 200,
              "Jueves": 200,
              "Viernes": 300,
              "Sábado": 200
            }
          },
          "Chuleta (tacos)": {
            "mae": 53.333333333333336,
            "rmse": 53.47896782848375,
            "mape": 88.88888888888887,
            "errores_por_dia": {
              "Lunes": -56.0,
              "Martes": -48.0,
              "Miércoles": -54.0,
              "Jueves": -50.0,
              "Viernes": -52.0,
              "Sábado": -60.0
            },
            "predicciones": {
              "Lunes": 4.0,
              "Martes": 12.0,
              "Miércoles": 6.0,
              "Jueves": 10.0,
              "Viernes": 8.0,
              "Sábado": 0.0
            },
            "reales": {
              "Lunes": 60,
              "Martes": 60,
              "Miércoles": 60,
              "Jueves": 60,
              "Viernes": 60,
              "Sábado": 60
            }
          },
          "Arrachera (tacos)": {
            "mae": 167.33333333333334,
            "rmse": 169.89800862085858,
            "mape": 91.53174603174602,
            "errores_por_dia": {
              "Lunes": -168.0,
              "Martes": -130.0,
              "Miércoles": -140.0,
              "Jueves": -188.0,
              "Viernes": -218.0,
              "Sábado": -160.0
            },
            "predicciones": {
              "Lunes": 32.0,
              "Martes": 10.0,
              "Miércoles": 20.0,
              "Jueves": 12.0,
              "Viernes": 22.0,
              "Sábado": 0.0
            },
            "reales": {
              "Lunes": 200,
              "Martes": 140,
              "Miércoles": 160,
              "Jueves": 200,
              "Viernes": 240,
              "Sábado": 160
            }
          },
          "Costilla (tacos)": {
            "mae": 100.66666666666667,
            "rmse": 103.79306335203717,
            "mape": 85.81944444444444,
            "errores_por_dia": {
              "Lunes": -94.0,
              "Martes": -73.0,
              "Miércoles": -89.0,
              "Jueves": -94.0,
              "Viernes": -154.0,
              "Sábado": -100.0
            },
            "predicciones": {
              "Lunes": 26.0,
              "Martes": 27.000000000000004,
              "Miércoles": 11.0,
              "Jueves": 26.0,
              "Viernes": 6.0,
              "Sábado": 0.0
            },
            "reales": {
              "Lunes": 120,
              "Martes": 100,
              "Miércoles": 100,
              "Jueves": 120,
              "Viernes": 160,
              "Sábado": 100
            }
          },
          "Coca (piezas)": {
            "mae": 46.333333333333336,
            "rmse": 51.68816756924806,
            "mape": 57.21036451471233,
            "errores_por_dia": {
              "Lunes": -46.0,
              "Martes": -40.0,
              "Miércoles": -5.999999999999993,
              "Jueves": -40.99999999999999,
              "Viernes": -79.0,
              "Sábado": -66.0
            },
            "predicciones": {
              "Lunes": 46.0,
              "Martes": 26.0,
              "Miércoles": 60.00000000000001,
              "Jueves": 51.00000000000001,
              "Viernes": 21.0,
              "Sábado": 0.0
            },
            "reales": {
              "Lunes": 92,
              "Martes": 66,
              "Miércoles": 66,
              "Jueves": 92,
              "Viernes": 100,
              "Sábado": 66
            }
          },
          "Mundet (piezas)": {
            "mae": 47.166666666666664,
            "rmse": 47.544715794712666,
            "mape": 82.75523088023088,
            "errores_por_dia": {
              "Lunes": -56.0,
              "Martes": -40.0,
              "Miércoles": -39.0,
              "Jueves": -49.0,
              "Viernes": -51.0,
              "Sábado": -48.0
            },
            "predicciones": {
              "Lunes": 10.0,
              "Martes": 8.0,
              "Miércoles": 9.0,
              "Jueves": 17.0,
              "Viernes": 19.0,
              "Sábado": 0.0
            },
            "reales": {
              "Lunes": 66,
              "Martes": 48,
              "Miércoles": 48,
              "Jueves": 66,
              "Viernes": 70,
              "Sábado": 48
            }
          }
        },
        "por_dia": {
          "Lunes": {
            "mae": 117.875,
            "rmse": 132.52782726657824,
            "mape": 77.21022727272727,
            "total_predicho": 295.0,
            "total_real": 1238.0
          },
          "Martes": {
            "mae": 106.0,
            "rmse": 121.65011302912957,
            "mape": 81.40165043290042,
            "total_predicho": 166.0,
            "total_real": 1014.0
          },
          "Miércoles": {
            "mae": 104.0,
            "rmse": 122.20576909458899,
            "mape": 76.19886363636363,
            "total_predicho": 202.0,
            "total_real": 1034.0
          },
          "Jueves": {
            "mae": 125.125,
            "rmse": 143.05374864015275,
            "mape": 78.53845520421606,
            "total_predicho": 237.0,
            "total_real": 1238.0
          },
          "Viernes": {
            "mae": 155.375,
            "rmse": 176.20832840703076,
            "mape": 85.49255952380952,
            "total_predicho": 187.0,
            "total_real": 1430.0
          },
          "Sábado": {
            "mae": 124.25,
            "rmse": 137.5954214354533,
            "mape": 100.0,
            "total_predicho": 0.0,
            "total_real": 994.0
          }
        }
      },
      "escalada": {
        "global": {
          "mae": 46.25,
          "rmse": 71.86213653007171,
          "r2_score": 0.11848277186456468,
          "mape": 32.900354476441436,
          "total_predicho": 6840.0,
          "total_real": 6948.0
        },
        "por_producto": {
          "Pollo (tacos)": {
            "mae": 48.333333333333336,
            "rmse": 69.6419413859206,
            "mape": 28.333333333333332,
            "errores_por_dia": {
              "Lunes": 30.0,
              "Martes": 20.0,
              "Miércoles": 20.0,
              "Jueves": 30.0,
              "Viernes": 30.0,
              "Sábado": -160.0
            },
            "predicciones": {
              "Lunes": 230.0,
              "Martes": 180.0,
              "Miércoles": 180.0,
              "Jueves": 230.0,
              "Viernes": 230.0,
              "Sábado": 0.0
            },
            "factores": {
              "Lunes": 2.6315789473684212,
              "Martes": 8.88888888888889,
              "Miércoles": 4.705882352941177,
              "Jueves": 5.882352941176471,
              "Viernes": 7.142857142857143,
              "Sábado": 5.882352941176471
            },
            "reales": {
              "Lunes": 200,
              "Martes": 160,
              "Miércoles": 160,
              "Jueves": 200,
              "Viernes": 200,
              "Sábado": 160
            }
          },
          "Bistec (tacos)": {
            "mae": 66.66666666666667,
            "rmse": 89.44271909999159,
            "mape": 28.888888888888886,
            "errores_por_dia": {
              "Lunes": 40.0,
              "Martes": 40.0,
              "Miércoles": 40.0,
              "Jueves": 40.0,
              "Viernes": 40.0,
              "Sábado": -200.0
            },
            "predicciones": {
              "Lunes": 340.0,
              "Martes": 280.0,
              "Miércoles": 280.0,
              "Jueves": 340.0,
              "Viernes": 340.0,
              "Sábado": 0.0
            },
            "factores": {
              "Lunes": 3.1914893617021276,
              "Martes": 3.870967741935484,
              "Miércoles": 4.0,
              "Jueves": 3.488372093023256,
              "Viernes": 3.9473684210526314,
              "Sábado": 3.870967741935484
            },
            "reales": {
              "Lunes": 300,
              "Martes": 240,
              "Miércoles": 240,
              "Jueves": 300,
              "Viernes": 300,
              "Sábado": 200
            }
          },
          "Longaniza (tacos)": {
            "mae": 111.66666666666667,
            "rmse": 139.22404006971402,
            "mape": 49.166666666666664,
            "errores_por_dia": {
              "Lunes": 30.0,
              "Martes": 30.0,
              "Miércoles": -50.0,
              "Jueves": -120.0,
              "Viernes": 240.0,
              "Sábado": -200.0
            },
            "predicciones": {
              "Lunes": 230.0,
              "Martes": 230.0,
              "Miércoles": 150.0,
              "Jueves": 80.0,
              "Viernes": 540.0,
              "Sábado": 0.0
            },
            "factores": {
              "Lunes": 28.571428571428573,
              "Martes": 66.66666666666667,
              "Miércoles": 66.66666666666667,
              "Jueves": 66.66666666666667,
              "Viernes": 66.66666666666667,
              "Sábado": 66.66666666666667
            },
            "reales": {
              "Lunes": 200,
              "Martes": 200,
              "Miércoles": 200,
              "Jueves": 200,
              "Viernes": 300,
              "Sábado": 200
            }
          },
          "Chuleta (tacos)": {
            "mae": 18.333333333333332,
            "rmse": 26.14064523559687,
            "mape": 30.555555555555554,
            "errores_por_dia": {
              "Lunes": 10.0,
              "Martes": 10.0,
              "Miércoles": 10.0,
              "Jueves": 10.0,
              "Viernes": 10.0,
              "Sábado": -60.0
            },
            "predicciones": {
              "Lunes": 70.0,
              "Martes": 70.0,
              "Miércoles": 70.0,
              "Jueves": 70.0,
              "Viernes": 70.0,
              "Sábado": 0.0
            },
            "factores": {
              "Lunes": 15.0,
              "Martes": 5.0,
              "Miércoles": 10.0,
              "Jueves": 6.0,
              "Viernes": 7.5,
              "Sábado": 7.5
            },
            "reales": {
              "Lunes": 60,
              "Martes": 60,
              "Miércoles": 60,
              "Jueves": 60,
              "Viernes": 60,
              "Sábado": 60
            }
          },
          "Arrachera (tacos)": {
            "mae": 50.0,
            "rmse": 70.47458170621992,
            "mape": 28.90873015873016,
            "errores_por_dia": {
              "Lunes": 30.0,
              "Martes": 20.0,
              "Miércoles": 20.0,
              "Jueves": 30.0,
              "Viernes": 40.0,
              "Sábado": -160.0
            },
            "predicciones": {
              "Lunes": 230.0,
              "Martes": 160.0,
              "Miércoles": 180.0,
              "Jueves": 230.0,
              "Viernes": 280.0,
              "Sábado": 0.0
            },
            "factores": {
              "Lunes": 6.25,
              "Martes": 14.0,
              "Miércoles": 8.0,
              "Jueves": 16.666666666666668,
              "Viernes": 10.909090909090908,
              "Sábado": 10.909090909090908
            },
            "reales": {
              "Lunes": 200,
              "Martes": 140,
              "Miércoles": 160,
              "Jueves": 200,
              "Viernes": 240,
              "Sábado": 160
            }
          },
          "Costilla (tacos)": {
            "mae": 33.333333333333336,
            "rmse": 44.721359549995796,
            "mape": 30.972222222222218,
            "errores_por_dia": {
              "Lunes": 20.0,
              "Martes": 20.0,
              "Miércoles": 20.0,
              "Jueves": 20.0,
              "Viernes": 20.0,
              "Sábado": -100.0
            },
            "predicciones": {
              "Lunes": 140.0,
              "Martes": 120.0,
              "Miércoles": 120.0,
              "Jueves": 140.0,
              "Viernes": 180.0,
              "Sábado": 0.0
            },
            "factores": {
              "Lunes": 4.615384615384615,
              "Martes": 3.7037037037037037,
              "Miércoles": 9.090909090909092,
              "Jueves": 4.615384615384615,
              "Viernes": 26.666666666666668,
              "Sábado": 4.615384615384615
            },
            "reales": {
              "Lunes": 120,
              "Martes": 100,
              "Miércoles": 100,
              "Jueves": 120,
              "Viernes": 160,
              "Sábado": 100
            }
          },
          "Coca (piezas)": {
            "mae": 23.333333333333332,
            "rmse": 30.265491900843113,
            "mape": 31.925779534475186,
            "errores_por_dia": {
              "Lunes": 18.0,
              "Martes": 14.0,
              "Miércoles": 14.0,
              "Jueves": 18.0,
              "Viernes": 10.0,
              "Sábado": -66.0
            },
            "predicciones": {
              "Lunes": 110.0,
              "Martes": 80.0,
              "Miércoles": 80.0,
              "Jueves": 110.0,
              "Viernes": 110.0,
              "Sábado": 0.0
            },
            "factores": {
              "Lunes": 2.0,
              "Martes": 2.5384615384615383,
              "Miércoles": 1.1,
              "Jueves": 1.803921568627451,
              "Viernes": 4.761904761904762,
              "Sábado": 2.0
            },
            "reales": {
              "Lunes": 92,
              "Martes": 66,
              "Miércoles": 66,
              "Jueves": 92,
              "Viernes": 100,
              "Sábado": 66
            }
          },
          "Mundet (piezas)": {
            "mae": 18.333333333333332,
            "rmse": 22.67156809750927,
            "mape": 34.45165945165945,
            "errores_por_dia": {
              "Lunes": 14.0,
              "Martes": 12.0,
              "Miércoles": 12.0,
              "Jueves": 14.0,
              "Viernes": 10.0,
              "Sábado": -48.0
            },
            "predicciones": {
              "Lunes": 80.0,
              "Martes": 60.0,
              "Miércoles": 60.0,
              "Jueves": 80.0,
              "Viernes": 80.0,
              "Sábado": 0.0
            },
            "factores": {
              "Lunes": 6.6,
              "Martes": 6.0,
              "Miércoles": 5.333333333333333,
              "Jueves": 3.8823529411764706,
              "Viernes": 3.6842105263157894,
              "Sábado": 5.333333333333333
            },
            "reales": {
              "Lunes": 66,
              "Martes": 48,
              "Miércoles": 48,
              "Jueves": 66,
              "Viernes": 70,
              "Sábado": 48
            }
          }
        },
        "por_dia": {
          "Lunes": {
            "mae": 24.0,
            "rmse": 25.787593916455254,
            "mape": 16.555500658761527,
            "total_predicho": 1430.0,
            "total_real": 1238.0
          },
          "Martes": {
            "mae": 20.75,
            "rmse": 22.74862633215465,
            "mape": 17.666396103896105,
            "total_predicho": 1180.0,
            "total_real": 1014.0
          },
          "Miércoles": {
            "mae": 23.25,
            "rmse": 26.78619047195775,
            "mape": 18.69318181818182,
            "total_predicho": 1120.0,
            "total_real": 1034.0
          },
          "Jueves": {
            "mae": 35.25,
            "rmse": 48.5025772511111,
            "mape": 22.180500658761527,
            "total_predicho": 1280.0,
            "total_real": 1238.0
          },
          "Viernes": {
            "mae": 50.0,
            "rmse": 88.31760866327846,
            "mape": 22.30654761904762,
            "total_predicho": 1830.0,
            "total_real": 1430.0
          },
          "Sábado": {
            "mae": 124.25,
            "rmse": 137.5954214354533,
            "mape": 100.0,
            "total_predicho": 0.0,
            "total_real": 994.0
          }
        }
      },
      "mejora": {
        "mae_mejora_pct": 62.122504692032074,
        "mape_mejora_pct": 60.427906353745286
      }
    }
  },
  "predicciones": {
    "Pollo (tacos)": {
      "Lunes": {
        "pred_base": 76.0,
        "factor_escala": 2.6315789473684212,
        "pred_escalada": 230.0
      },
      "Martes": {
        "pred_base": 18.0,
        "factor_escala": 8.88888888888889,
        "pred_escalada": 180.0
      },
      "Miércoles": {
        "pred_base": 34.0,
        "factor_escala": 4.705882352941177,
        "pred_escalada": 180.0
      },
      "Jueves": {
        "pred_base": 34.0,
        "factor_escala": 5.882352941176471,
        "pred_escalada": 230.0
      },
      "Viernes": {
        "pred_base": 28.0,
        "factor_escala": 7.142857142857143,
        "pred_escalada": 230.0
      },
      "Sábado": {
        "pred_base": 0.0,
        "factor_escala": 5.882352941176471,
        "pred_escalada": 0.0
      }
    },
    "Bistec (tacos)": {
      "Lunes": {
        "pred_base": 94.0,
        "factor_escala": 3.1914893617021276,
        "pred_escalada": 340.0
      },
      "Martes": {
        "pred_base": 62.0,
        "factor_escala": 3.870967741935484,
        "pred_escalada": 280.0
      },
      "Miércoles": {
        "pred_base": 59.99999999999999,
        "factor_escala": 4.0,
        "pred_escalada": 280.0
      },
      "Jueves": {
        "pred_base": 86.0,
        "factor_escala": 3.488372093023256,
        "pred_escalada": 340.0
      },
      "Viernes": {
        "pred_base": 76.0,
        "factor_escala": 3.9473684210526314,
        "pred_escalada": 340.0
      },
      "Sábado": {
        "pred_base": 0.0,
        "factor_escala": 3.870967741935484,
        "pred_escalada": 0.0
      }
    },
    "Longaniza (tacos)": {
      "Lunes": {
        "pred_base": 7.0,
        "factor_escala": 28.571428571428573,
        "pred_escalada": 230.0
      },
      "Martes": {
        "pred_base": 3.0,
        "factor_escala": 66.66666666666667,
        "pred_escalada": 230.0
      },
      "Miércoles": {
        "pred_base": 2.0,
        "factor_escala": 66.66666666666667,
        "pred_escalada": 150.0
      },
      "Jueves": {
        "pred_base": 1.0,
        "factor_escala": 66.66666666666667,
        "pred_escalada": 80.0
      },
      "Viernes": {
        "pred_base": 7.0,
        "factor_escala": 66.66666666666667,
        "pred_escalada": 540.0
      },
      "Sábado": {
        "pred_base": 0.0,
        "factor_escala": 66.66666666666667,
        "pred_escalada": 0.0
      }
    },
    "Chuleta (tacos)": {
      "Lunes": {
        "pred_base": 4.0,
        "factor_escala": 15.0,
        "pred_escalada": 70.0
      },
      "Martes": {
        "pred_base": 12.0,
        "factor_escala": 5.0,
        "pred_escalada": 70.0
      },
      "Miércoles": {
        "pred_base": 6.0,
        "factor_escala": 10.0,
        "pred_escalada": 70.0
      },
      "Jueves": {
        "pred_base": 10.0,
        "factor_escala": 6.0,
        "pred_escalada": 70.0
      },
      "Viernes": {
        "pred_base": 8.0,
        "factor_escala": 7.5,
        "pred_escalada": 70.0
      },
      "Sábado": {
        "pred_base": 0.0,
        "factor_escala": 7.5,
        "pred_escalada": 0.0
      }
    },
    "Arrachera (tacos)": {
      "Lunes": {
        "pred_base": 32.0,
        "factor_escala": 6.25,
        "pred_escalada": 230.0
      },
      "Martes": {
        "pred_base": 10.0,
        "factor_escala": 14.0,
        "pred_escalada": 160.0
      },
      "Miércoles": {
        "pred_base": 20.0,
        "factor_escala": 8.0,
        "pred_escalada": 180.0
      },
      "Jueves": {
        "pred_base": 12.0,
        "factor_escala": 16.666666666666668,
        "pred_escalada": 230.0
      },
      "Viernes": {
        "pred_base": 22.0,
        "factor_escala": 10.909090909090908,
        "pred_escalada": 280.0
      },
      "Sábado": {
        "pred_base": 0.0,
        "factor_escala": 10.909090909090908,
        "pred_escalada": 0.0
      }
    },
    "Costilla (tacos)": {
      "Lunes": {
        "pred_base": 26.0,
        "factor_escala": 4.615384615384615,
        "pred_escalada": 140.0
      },
      "Martes": {
        "pred_base": 27.000000000000004,
        "factor_escala": 3.7037037037037037,
        "pred_escalada": 120.0
      },
      "Miércoles": {
        "pred_base": 11.0,
        "factor_escala": 9.090909090909092,
        "pred_escalada": 120.0
      },
      "Jueves": {
        "pred_base": 26.0,
        "factor_escala": 4.615384615384615,
        "pred_escalada": 140.0
      },
      "Viernes": {
        "pred_base": 6.0,
        "factor_escala": 26.666666666666668,
        "pred_escalada": 180.0
      },
      "Sábado": {
        "pred_base": 0.0,
        "factor_escala": 4.615384615384615,
        "pred_escalada": 0.0
      }
    },
    "Coca (piezas)": {
      "Lunes": {
        "pred_base": 46.0,
        "factor_escala": 2.0,
        "pred_escalada": 110.0
      },
      "Martes": {
        "pred_base": 26.0,
        "factor_escala": 2.5384615384615383,
        "pred_escalada": 80.0
      },
      "Miércoles": {
        "pred_base": 60.00000000000001,
        "factor_escala": 1.1,
        "pred_escalada": 80.0
      },
      "Jueves": {
        "pred_base": 51.00000000000001,
        "factor_escala": 1.803921568627451,
        "pred_escalada": 110.0
      },
      "Viernes": {
        "pred_base": 21.0,
        "factor_escala": 4.761904761904762,
        "pred_escalada": 110.0
      },
      "Sábado": {
        "pred_base": 0.0,
        "factor_escala": 2.0,
        "pred_escalada": 0.0
      }
    },
    "Mundet (piezas)": {
      "Lunes": {
        "pred_base": 10.0,
        "factor_escala": 6.6,
        "pred_escalada": 80.0
      },
      "Martes": {
        "pred_base": 8.0,
        "factor_escala": 6.0,
        "pred_escalada": 60.0
      },
      "Miércoles": {
        "pred_base": 9.0,
        "factor_escala": 5.333333333333333,
        "pred_escalada": 60.0
      },
      "Jueves": {
        "pred_base": 17.0,
        "factor_escala": 3.8823529411764706,
        "pred_escalada": 80.0
      },
      "Viernes": {
        "pred_base": 19.0,
        "factor_escala": 3.6842105263157894,
        "pred_escalada": 80.0
      },
      "Sábado": {
        "pred_base": 0.0,
        "factor_escala": 5.333333333333333,
        "pred_escalada": 0.0
      }
    }
  },
  "compras_reales": {
    "Pollo (tacos)": {
      "Lunes": 200,
      "Martes": 160,
      "Miércoles": 160,
      "Jueves": 200,
      "Viernes": 200,
      "Sábado": 160
    },
    "Bistec (tacos)": {
      "Lunes": 300,
      "Martes": 240,
      "Miércoles": 240,
      "Jueves": 300,
      "Viernes": 300,
      "Sábado": 200
    },
    "Longaniza (tacos)": {
      "Lunes": 200,
      "Martes": 200,
      "Miércoles": 200,
      "Jueves": 200,
      "Viernes": 300,
      "Sábado": 200
    },
    "Chuleta (tacos)": {
      "Lunes": 60,
      "Martes": 60,
      "Miércoles": 60,
      "Jueves": 60,
      "Viernes": 60,
      "Sábado": 60
    },
    "Arrachera (tacos)": {
      "Lunes": 200,
      "Martes": 140,
      "Miércoles": 160,
      "Jueves": 200,
      "Viernes": 240,
      "Sábado": 160
    },
    "Costilla (tacos)": {
      "Lunes": 120,
      "Martes": 100,
      "Miércoles": 100,
      "Jueves": 120,
      "Viernes": 160,
      "Sábado": 100
    },
    "Coca (piezas)": {
      "Lunes": 92,
      "Martes": 66,
      "Miércoles": 66,
      "Jueves": 92,
      "Viernes": 100,
      "Sábado": 66
    },
    "Mundet (piezas)": {
      "Lunes": 66,
      "Martes": 48,
      "Miércoles": 48,
      "Jueves": 66,
      "Viernes": 70,
      "Sábado": 48
    }
  }
}